fargv/__init__.py
fargv/arg_types.py
fargv/argv_parser.py
fargv/dict_parser.py
fargv/util.py
fargv-0.1.8.dist-info/LICENSE.txt
fargv-0.1.8.dist-info/METADATA
fargv-0.1.8.dist-info/WHEEL
fargv-0.1.8.dist-info/top_level.txt
fargv-0.1.8.dist-info/RECORD
