Metadata-Version: 2.1
Name: fargv
Version: 0.1.8
Summary: A very easy to use argument parser.
Home-page: https://github.com/anguelos/fargv
Author: Anguelos Nicolaou
Author-email: anguelos.nicolaou@gmail.com
License: MIT
Keywords: argv,CLI,argument
Platform: any
Classifier: Intended Audience :: Science/Research
Classifier: Programming Language :: Python :: 3.6
Classifier: Programming Language :: Python :: 3.7
Classifier: Programming Language :: Python :: 3.8
Classifier: Programming Language :: Python :: 3.10
Classifier: Topic :: Scientific/Engineering
Requires-Python: >=3.6
License-File: LICENSE.txt
